fastanpr/__init__.py
fastanpr/best.pt
fastanpr/detection.py
fastanpr/fastanpr.py
fastanpr/numberplate.py
fastanpr/recognition.py
fastanpr/version.py
fastanpr-0.1.13.dist-info/LICENSE
fastanpr-0.1.13.dist-info/METADATA
fastanpr-0.1.13.dist-info/WHEEL
fastanpr-0.1.13.dist-info/top_level.txt
fastanpr-0.1.13.dist-info/RECORD
