Metadata-Version: 2.1
Name: fastanpr
Version: 0.1.13
Summary: A fast automatic number-plate recognition (ANPR) library
Home-page: https://github.com/arvindrajan92/fastanpr
Author: arvindrajan92 (Arvind Rajan)
Author-email: <arvindrajan92@gmail.com>
Keywords: python,anpr,fast,licence plate,number plate,detection,recognition,YOLOv8,paddleocr,paddlepaddle
Classifier: Programming Language :: Python :: 3.8
Classifier: Programming Language :: Python :: 3.9
Classifier: Programming Language :: Python :: 3.10
Classifier: Programming Language :: Python :: 3.11
Classifier: License :: OSI Approved :: GNU Affero General Public License v3 or later (AGPLv3+)
Classifier: Operating System :: OS Independent
Requires-Python: >=3.6
License-File: LICENSE
Requires-Dist: ultralytics >=8.1.34
Requires-Dist: paddlepaddle >=2.6.1
Requires-Dist: paddleocr ==2.7.2
Requires-Dist: pydantic >=2.6.4
Provides-Extra: dev
Requires-Dist: pytest ; extra == 'dev'
Requires-Dist: pytest-asyncio ; extra == 'dev'
Requires-Dist: twine ; extra == 'dev'
Requires-Dist: python-Levenshtein ; extra == 'dev'
Requires-Dist: setuptools ; extra == 'dev'
Requires-Dist: wheel ; extra == 'dev'
Requires-Dist: flake8 ; extra == 'dev'
